sdf/__init__.py
sdf/dsres.py
sdf/hdf5.py
sdf/units.py
sdf/examples/IntegerNetwork1.xlsx
sdf/examples/__init__.py
sdf/examples/excel2sdf.py
sdf/examples/interp_1d.py
sdf/examples/interp_2d.py
sdf/examples/plot_dymola_result.py
sdf/examples/sine.py
sdf/examples/spline_1d.py
sdf/ndtable/__init__.py
sdf/plot/contour_plot.py
sdf/plot/contour_plot_3d.py
sdf/plot/plot_time_series.py
sdf/examples/IntegerNetwork1.mat
sdf/examples/time_series.xlsx
sdf/ndtable/aarch64-darwin/libNDTable.dylib
sdf/ndtable/x86_64-darwin/libNDTable.dylib
sdf/ndtable/x86_64-linux/libNDTable.so
sdf/ndtable/x86_64-windows/NDTable.dll
sdf-0.3.7.dist-info/METADATA
sdf-0.3.7.dist-info/WHEEL
sdf-0.3.7.dist-info/licenses/LICENSE
sdf-0.3.7.dist-info/RECORD
