Metadata-Version: 2.4
Name: SDF
Version: 0.3.7
Summary: Work with Scientific Data Format files in Python
License-File: LICENSE
Requires-Python: >=3.10
Requires-Dist: attrs>=25.3.0
Requires-Dist: h5py>=3.13.0
Requires-Dist: matplotlib>=3.10.3
Requires-Dist: numpy>=2.2.6
Requires-Dist: scipy>=1.15.3
Requires-Dist: xlrd>=2.0.1
